spartaabc/__init__.py
spartaabc/abc_inference.py
spartaabc/aligner_interface.py
spartaabc/correction.py
spartaabc/correction_utilities.py
spartaabc/default_prior.json
spartaabc/main.py
spartaabc/prior_sampler.py
spartaabc/raxml_parser.py
spartaabc/simulate_data.py
spartaabc/test.py
spartaabc/utility.py
spartaabc/getting_priors/__init__.py
spartaabc/getting_priors/geometric.py
spartaabc/getting_priors/get_means.py
spartaabc/getting_priors/poisson.py
spartaabc/getting_priors/zipf.py
spartaabc-0.8.0.dist-info/METADATA
spartaabc-0.8.0.dist-info/WHEEL
spartaabc-0.8.0.dist-info/entry_points.txt
spartaabc-0.8.0.dist-info/top_level.txt
spartaabc-0.8.0.dist-info/RECORD
