Metadata-Version: 2.4
Name: spartaabc
Version: 0.8.0
Summary: Indel model parameter inference.
License: AFL-3.0
Requires-Dist: scikit-learn
Requires-Dist: pandas
Requires-Dist: pyarrow
Requires-Dist: msasim
Requires-Dist: msastats
Requires-Dist: itaxotools-mafftpy
